cipher_yx2625/__init__.py
cipher_yx2625/cipher_yx2625.py
cipher_yx2625-0.1.0.dist-info/LICENSE
cipher_yx2625-0.1.0.dist-info/WHEEL
cipher_yx2625-0.1.0.dist-info/METADATA
cipher_yx2625-0.1.0.dist-info/RECORD
